preloop/cli/__init__.py
preloop/cli/main.py
preloop/cli/utils/__init__.py
preloop/cli/utils/enums.py
preloop_cli-0.3.18.dist-info/LICENSE
preloop_cli-0.3.18.dist-info/METADATA
preloop_cli-0.3.18.dist-info/WHEEL
preloop_cli-0.3.18.dist-info/entry_points.txt
preloop_cli-0.3.18.dist-info/RECORD
