Metadata-Version: 2.1
Name: preloop-cli
Version: 0.3.18
Summary: Command line interface to access Preloop.
Home-page: https://www.preloop.com/
License: Apache-2.0
Keywords: preloop,cli
Author: Preloop, Inc.
Author-email: engineering@preloop.com
Requires-Python: >=3.11,<4.0
Classifier: License :: OSI Approved :: Apache Software License
Classifier: Programming Language :: Python :: 3
Classifier: Programming Language :: Python :: 3.11
Requires-Dist: preloop-sdk (>=0.2.14,<0.3.0)
Requires-Dist: pyarrow (>=14.0.1,<15.0.0)
Requires-Dist: rich (>=13.7.0,<14.0.0)
Requires-Dist: typer (>=0.9.0,<0.10.0)
Project-URL: Documentation, https://www.preloop.com/docs
